cachu/__init__.py
cachu/cache.py
cachu/config.py
cachu/decorator.py
cachu/keys.py
cachu/operations.py
cachu/types.py
cachu/backends/__init__.py
cachu/backends/file.py
cachu/backends/memory.py
cachu/backends/redis.py
cachu-0.1.3.dist-info/METADATA
cachu-0.1.3.dist-info/WHEEL
cachu-0.1.3.dist-info/top_level.txt
cachu-0.1.3.dist-info/RECORD
