Metadata-Version: 2.4
Name: cachu
Version: 0.1.3
Summary: Flexible caching library built on dogpile.cache
Author: bissli
License-Expression: 0BSD
Project-URL: Repository, https://github.com/bissli/cachu.git
Requires-Python: >=3.10
Requires-Dist: dogpile.cache
Requires-Dist: func-timeout
Provides-Extra: redis
Requires-Dist: redis; extra == "redis"
Provides-Extra: test
Requires-Dist: pytest; extra == "test"
Requires-Dist: pytest-mock; extra == "test"
Requires-Dist: redis; extra == "test"
Requires-Dist: testcontainers[redis]; extra == "test"
